renameit/__main__.py
renameit/core/__init__.py
renameit/core/cli.py
renameit/core/exceptions.py
renameit/core/job_runners.py
renameit/core/models.py
renameit/core/util.py
renameit/core/config/__init__.py
renameit/core/config/parse.py
renameit/core/config/project.py
renameit/file_systems/aws.py
renameit/file_systems/azure.py
renameit/file_systems/google.py
renameit/file_systems/interfaces.py
renameit/file_systems/local.py
renameit/handlers/basic.py
renameit/handlers/datetime.py
renameit/handlers/interfaces.py
renameit/handlers/regex.py
tests/__init__.py
tests/conftest.py
tests/core/__init__.py
tests/core/test_cli.py
tests/file_systems/__init__.py
tests/file_systems/test_aws.py
tests/file_systems/test_azure.py
tests/file_systems/test_google.py
tests/file_systems/test_local.py
tests/handlers/__init__.py
tests/handlers/test_basic.py
tests/handlers/test_datetime.py
tests/handlers/test_regex.py
renameit-0.1.0a0.dist-info/LICENSE.txt
renameit-0.1.0a0.dist-info/METADATA
renameit-0.1.0a0.dist-info/WHEEL
renameit-0.1.0a0.dist-info/entry_points.txt
renameit-0.1.0a0.dist-info/top_level.txt
renameit-0.1.0a0.dist-info/RECORD
