Metadata-Version: 2.1
Name: renameit
Version: 0.1.0a0
Summary: File renaming tool
Home-page: https://github.com/Hasan-J/renameit
Author: Hasan Jawad
Author-email: hasan_sg@hotmail.com
License: MIT
Keywords: rename, copy, files, renaming,,naming files, refactor, file names,datalake, azure, aws, gcp, google
Classifier: License :: OSI Approved :: MIT License
Classifier: Programming Language :: Python :: 3.10
Classifier: Natural Language :: English
Requires-Python: >=3.10
License-File: LICENSE.txt
Requires-Dist: fire (==0.4.0)
Requires-Dist: pydantic (==1.9.1)
Requires-Dist: confight[yaml] (==1.3.1)
Provides-Extra: aws
Requires-Dist: boto3 (==1.24.15) ; extra == 'aws'
Provides-Extra: azure
Requires-Dist: azure-identity (==1.10.0) ; extra == 'azure'
Requires-Dist: azure-storage-file-datalake (==12.7.0) ; extra == 'azure'
Provides-Extra: google
Requires-Dist: google-cloud-storage (==2.4.0) ; extra == 'google'
